pymindiff/__init__.py
pymindiff/groups.py
pymindiff/partitions.py
pymindiff/scale.py
pymindiff-1.0.dist-info/LICENSE
pymindiff-1.0.dist-info/METADATA
pymindiff-1.0.dist-info/WHEEL
pymindiff-1.0.dist-info/top_level.txt
pymindiff-1.0.dist-info/RECORD
