Metadata-Version: 2.1
Name: pymindiff
Version: 1.0
Summary: A Python-package to create fair groups having minimal differences
Home-page: https://github.com/Simbamoureux/pymindiff
Author: Clément Lombard
Author-email: clementlombard@orange.fr
License: UNKNOWN
Platform: UNKNOWN
Classifier: Programming Language :: Python :: 3
Classifier: License :: OSI Approved :: MIT License
Classifier: Operating System :: OS Independent
Requires-Python: >=3.6
